.gitignore
LICENSE
README
README.md
setup.py
sites.yaml
simple_site_manager/__init__.py
simple_site_manager/siteman.py
simple_site_manager.egg-info/PKG-INFO
simple_site_manager.egg-info/SOURCES.txt
simple_site_manager.egg-info/dependency_links.txt
simple_site_manager.egg-info/entry_points.txt
simple_site_manager.egg-info/pbr.json
simple_site_manager.egg-info/requires.txt
simple_site_manager.egg-info/top_level.txt
simple_site_manager/templates/fcgi.py.jinja2
simple_site_manager/templates/lighttpd.conf.jinja2