Metadata-Version: 1.1
Name: simple-site-manager
Version: 0.1.7
Summary: Manage multiple lighttpd and Django or Flask websites on a single machine. 
Home-page: https://github.com/zeraien/simple-site-manager
Author: Dmitri Fedortchenko
Author-email: info@onedaybeard.com
License: MIT
Keywords: lighttpd fcgi tool management
Platform: UNKNOWN
Classifier: Development Status :: 3 - Alpha
Classifier: Intended Audience :: Developers
Classifier: Topic :: System :: Software Distribution
Classifier: Topic :: System :: Systems Administration
Classifier: License :: OSI Approved :: MIT License
Classifier: Programming Language :: Python :: 2
Classifier: Programming Language :: Python :: 2.6
Classifier: Programming Language :: Python :: 2.7
Classifier: Programming Language :: Python :: 3
Classifier: Programming Language :: Python :: 3.2
Classifier: Programming Language :: Python :: 3.3
Classifier: Programming Language :: Python :: 3.4
